grznda/__init__.py
grznda/__main__.py
grznda/grznda.py
grznda-0.0.1.dist-info/LICENSE
grznda-0.0.1.dist-info/METADATA
grznda-0.0.1.dist-info/WHEEL
grznda-0.0.1.dist-info/top_level.txt
grznda-0.0.1.dist-info/RECORD
